cli/__init__.py
cli/cli.py
cli/main.py
compression/__init__.py
compression/compression_algorithms.py
core/__init__.py
core/base_tokenizer.py
core/core_tokenizer.py
core/parallel_tokenizer.py
core/santok_engine.py
embeddings/__init__.py
embeddings/embedding_generator.py
embeddings/inference_pipeline.py
embeddings/semantic_trainer.py
embeddings/vector_store.py
enhanced_semantic_trainer/__init__.py
enhanced_semantic_trainer/enhanced_trainer.py
enhanced_semantic_trainer/example_train.py
enhanced_semantic_trainer/example_use.py
integration/__init__.py
integration/vocabulary_adapter.py
interpretation/__init__.py
interpretation/data_interpreter.py
performance/__init__.py
performance/test_accuracy.py
santok/__init__.py
santok/cli.py
santok/santok.py
santok/utils/__init__.py
santok/utils/config.py
santok/utils/logging_config.py
santok/utils/validation.py
santok_complete-1.0.0.dist-info/licenses/LICENSE
servers/__init__.py
servers/lightweight_server.py
servers/main_server.py
src/__init__.py
src/demo_complete_workflow.py
src/santok_sources.py
src/cli/__init__.py
src/cli/decode_demo.py
src/cli/main.py
src/compression/__init__.py
src/compression/compression_algorithms.py
src/core/__init__.py
src/core/base_tokenizer.py
src/core/core_tokenizer.py
src/core/parallel_tokenizer.py
src/embeddings/__init__.py
src/embeddings/embedding_generator.py
src/embeddings/inference_pipeline.py
src/embeddings/semantic_trainer.py
src/embeddings/vector_store.py
src/embeddings/weaviate_vector_store.py
src/examples/__init__.py
src/examples/demo_enhanced_tokenization.py
src/examples/demo_stable_system.py
src/examples/demo_universal_files.py
src/examples/evaluate_semantics.py
src/integration/__init__.py
src/integration/source_map_integration.py
src/integration/vocabulary_adapter.py
src/interpretation/__init__.py
src/interpretation/data_interpreter.py
src/performance/__init__.py
src/performance/comprehensive_performance_test.py
src/performance/test_accuracy.py
src/performance/test_organized_outputs.py
src/servers/__init__.py
src/servers/admin_config.py
santok_complete-1.0.0.dist-info/METADATA
santok_complete-1.0.0.dist-info/WHEEL
santok_complete-1.0.0.dist-info/entry_points.txt
santok_complete-1.0.0.dist-info/top_level.txt
santok_complete-1.0.0.dist-info/RECORD
